kentigern/__init__.py
kentigern/bannerversion.html
kentigern/breadcrumbs.html
kentigern/darkmode.html
kentigern/darkmode.html~
kentigern/footer.html
kentigern/footer.html~
kentigern/globaltoc.html
kentigern/layout.html
kentigern/localtoc.html
kentigern/navbar-2.html
kentigern/navbar.html
kentigern/navbarlinks.html
kentigern/navbarsearchbox.html
kentigern/navbartoc.html
kentigern/relations.html
kentigern/repository.html
kentigern/repository.html~
kentigern/search.html
kentigern/searchbox.html
kentigern/searchresults.html
kentigern/sidebar-left.html
kentigern/sidebar-right.html
kentigern/sidebar.html
kentigern/sourcelink.html
kentigern/theme.conf
kentigern/versions.html
kentigern/versions.html~
kentigern/static/03070d12cdd1a2d5f864.woff2
kentigern/static/0573a2ae2e466eba0356.woff2
kentigern/static/06101a7ccf85875d015f.woff2
kentigern/static/0c07f750f73ac5437580.woff
kentigern/static/166e8e87ae0b6f3deed3.woff2
kentigern/static/1d8ea3d31970f45e1efa.woff2
kentigern/static/30200ae8affd2aa68d61.woff2
kentigern/static/3949bcd2a59f6821ff78.woff2
kentigern/static/39795c0b4513de014cf8.woff
kentigern/static/5093444cb297b626a03b.woff2
kentigern/static/522dc3f44dad5d0943a5.woff2
kentigern/static/66e3b28f5cc696a83179.woff2
kentigern/static/68d1b10af8c94cae0c25.woff2
kentigern/static/6a8bc7acd205391fb71a.woff2
kentigern/static/6c09b07bbd10f336c332.woff2
kentigern/static/7626380a00fc84de6c05.woff2
kentigern/static/775cfb1c0b9f305c75e6.woff2
kentigern/static/7df0968e0f981f08d253.woff
kentigern/static/7eca7ba7019410a77cd7.woff2
kentigern/static/add6a1fe8239b714d178.woff2
kentigern/static/admonitions.css_t
kentigern/static/b7bcc075b395c14ce8c2.woff2
kentigern/static/b8644b6e04ecda1cf98b.woff2
kentigern/static/bed6a02955440c361456.woff
kentigern/static/breadcrumbs.css_t
kentigern/static/c5289beecbadccb6af47.woff
kentigern/static/cc20b15eacd73fe42dfe.woff2
kentigern/static/code.css_t
kentigern/static/d0b4e727f79abb3cd315.woff2
kentigern/static/darkmode.js
kentigern-0.4.1.dist-info/LICENSE.txt
kentigern-0.4.1.dist-info/METADATA
kentigern-0.4.1.dist-info/WHEEL
kentigern-0.4.1.dist-info/entry_points.txt
kentigern-0.4.1.dist-info/top_level.txt
kentigern-0.4.1.dist-info/RECORD
