Metadata-Version: 2.1
Name: kentigern
Version: 0.4.1
Summary: A modern-looking Sphinx theme
Home-page: https://code.daniel-williams.co.uk/kentigern
Author: Daniel Williams
Author-email: mail@daniel-williams.co.uk
Classifier: Development Status :: 5 - Production/Stable
Classifier: Environment :: Web Environment
Classifier: Intended Audience :: Developers
Classifier: Intended Audience :: System Administrators
Classifier: License :: OSI Approved :: MIT License
Classifier: Operating System :: OS Independent
Classifier: Programming Language :: Python
Classifier: Programming Language :: Python :: 2
Classifier: Programming Language :: Python :: 3
Classifier: Topic :: Internet
Classifier: Topic :: Software Development :: Documentation
License-File: LICENSE.txt
Requires-Dist: setuptools
Requires-Dist: sphinx
Requires-Dist: sphinxcontrib-jquery
